README.md
setup.py
ini2json/__init__.py
ini2json/main.py
ini2json.egg-info/PKG-INFO
ini2json.egg-info/SOURCES.txt
ini2json.egg-info/dependency_links.txt
ini2json.egg-info/entry_points.txt
ini2json.egg-info/top_level.txt